ArverRubika/__init__.py
ArverRubika/ArverMaker/__init__.py
ArverRubika/cryptos/__init__.py
ArverRubika/servers/__init__.py
ArverRubika-2.0.1.dist-info/LICENSE
ArverRubika-2.0.1.dist-info/METADATA
ArverRubika-2.0.1.dist-info/WHEEL
ArverRubika-2.0.1.dist-info/top_level.txt
ArverRubika-2.0.1.dist-info/RECORD
