Metadata-Version: 2.1
Name: ArverRubika
Version: 2.0.1
Summary: Coding the robot in Rubika in the easiest way !
Author: Aboli Coder
Author-email: mirzaiabolfazl6@gmail.com
Keywords: python,rubel,Rubika,ArverRubika,robika,robot,ArseinRubika,arsein,arver,Arver,pyrubi
Classifier: Development Status :: 3 - Alpha
Classifier: Intended Audience :: Education
Classifier: License :: OSI Approved :: MIT License
Classifier: Programming Language :: Python :: 2
Classifier: Programming Language :: Python :: 3
License-File: LICENSE
Requires-Dist: pycryptodome (==3.16.0)
Requires-Dist: Pillow (==9.4.0)
